servicepy/__init__.py
servicepy-1.0.0.dist-info/METADATA
servicepy-1.0.0.dist-info/WHEEL
servicepy-1.0.0.dist-info/top_level.txt
servicepy-1.0.0.dist-info/RECORD
