Metadata-Version: 2.1
Name: servicepy
Version: 1.0.0
Summary: REST client to Service Now.
Home-page: https://github.com/samuelcorradi/servicepy
Author: Samuel Corradi
Author-email: samuelcorradi@gmail.com
Classifier: Programming Language :: Python :: 3
Classifier: License :: OSI Approved :: Apache Software License
Classifier: Operating System :: OS Independent
Classifier: Topic :: Database
Classifier: Topic :: Utilities
Requires-Python: >=3.7.8
